BGLogger
